normalize_tools/__init__.py
normalize_tools/countries.py
normalize_tools/phones.py
normalize_tools/traductions.py
normalize_tools/data/__init__.py
normalize_tools/tests/test_countries.py
normalize_tools/tests/test_country_from_phone.py
normalize_tools/tests/test_phones.py
normalize_tools-0.1.13.dist-info/METADATA
normalize_tools-0.1.13.dist-info/WHEEL
normalize_tools-0.1.13.dist-info/top_level.txt
normalize_tools-0.1.13.dist-info/RECORD
