Metadata-Version: 2.4
Name: normalize_tools
Version: 0.1.13
Summary: Herramientas de normalizacion de telefonos, y paises
Author-email: KC <rmr@keepcoding.io>
License-Expression: MIT
Project-URL: Homepage, https://github.com/KeepCoding/normalize_tools
Requires-Python: >=3.8
Requires-Dist: phonenumbers>=8.12.0
Requires-Dist: Unidecode==1.4.0
Requires-Dist: babel==2.17.0
Requires-Dist: unidecode==1.4.0
Requires-Dist: tldextract==5.3.0
Requires-Dist: geocoder==1.38.1
Requires-Dist: pycountry==24.6.1
